{
  "title": "JetStream Events",
  "uid": "jetstream-events",
  "version": 1,
  "schemaVersion": 38,
  "tags": ["nats", "jetstream", "events"],
  "timezone": "browser",
  "refresh": "15s",
  "time": { "from": "now-1h", "to": "now" },
  "panels": [
    {
      "id": 1,
      "title": "Agent Event Rate (5m)",
      "type": "stat",
      "gridPos": { "x": 0, "y": 0, "w": 6, "h": 4 },
      "datasource": { "type": "prometheus", "uid": "prometheus" },
      "targets": [
        {
          "expr": "sum(rate(hi_jetstream_events_total{subject_prefix=\"hi.agents\"}[5m]))",
          "legendFormat": "agent events/s",
          "refId": "A"
        }
      ],
      "options": {
        "reduceOptions": { "calcs": ["lastNotNull"] },
        "colorMode": "background"
      },
      "fieldConfig": {
        "defaults": { "unit": "ops" }
      }
    },
    {
      "id": 2,
      "title": "Task Event Rate (5m)",
      "type": "stat",
      "gridPos": { "x": 6, "y": 0, "w": 6, "h": 4 },
      "datasource": { "type": "prometheus", "uid": "prometheus" },
      "targets": [
        {
          "expr": "sum(rate(hi_jetstream_events_total{subject_prefix=\"hi.tasks\"}[5m]))",
          "legendFormat": "task events/s",
          "refId": "A"
        }
      ],
      "options": {
        "reduceOptions": { "calcs": ["lastNotNull"] },
        "colorMode": "background"
      },
      "fieldConfig": {
        "defaults": { "unit": "ops" }
      }
    },
    {
      "id": 3,
      "title": "Mean Task Completion Latency",
      "type": "stat",
      "gridPos": { "x": 12, "y": 0, "w": 6, "h": 4 },
      "datasource": { "type": "prometheus", "uid": "prometheus" },
      "targets": [
        {
          "expr": "hi_jetstream_task_latency_seconds{status=\"completed\"}",
          "legendFormat": "completion latency",
          "refId": "A"
        }
      ],
      "options": {
        "reduceOptions": { "calcs": ["lastNotNull"] },
        "colorMode": "value"
      },
      "fieldConfig": {
        "defaults": { "unit": "s" }
      }
    },
    {
      "id": 4,
      "title": "Consumer Connected",
      "type": "stat",
      "gridPos": { "x": 18, "y": 0, "w": 6, "h": 4 },
      "datasource": { "type": "prometheus", "uid": "prometheus" },
      "targets": [
        {
          "expr": "hi_jetstream_consumer_connected",
          "legendFormat": "connected",
          "refId": "A"
        }
      ],
      "options": {
        "reduceOptions": { "calcs": ["lastNotNull"] },
        "colorMode": "background",
        "thresholds": {
          "mode": "absolute",
          "steps": [
            { "color": "red", "value": null },
            { "color": "green", "value": 1 }
          ]
        }
      },
      "fieldConfig": {
        "defaults": {
          "mappings": [
            { "options": { "0": { "text": "Disconnected" }, "1": { "text": "Connected" } }, "type": "value" }
          ]
        }
      }
    },
    {
      "id": 5,
      "title": "Event Rate by Subject Prefix",
      "type": "timeseries",
      "gridPos": { "x": 0, "y": 4, "w": 24, "h": 8 },
      "datasource": { "type": "prometheus", "uid": "prometheus" },
      "targets": [
        {
          "expr": "sum by (subject_prefix) (rate(hi_jetstream_events_total[5m]))",
          "legendFormat": "{{subject_prefix}}",
          "refId": "A"
        }
      ],
      "fieldConfig": {
        "defaults": { "unit": "ops" }
      }
    },
    {
      "id": 6,
      "title": "Task Event Rate by Type",
      "type": "timeseries",
      "gridPos": { "x": 0, "y": 12, "w": 12, "h": 8 },
      "datasource": { "type": "prometheus", "uid": "prometheus" },
      "targets": [
        {
          "expr": "sum by (event_type) (rate(hi_jetstream_events_total{subject_prefix=\"hi.tasks\"}[5m]))",
          "legendFormat": "{{event_type}}",
          "refId": "A"
        }
      ],
      "fieldConfig": {
        "defaults": { "unit": "ops" }
      }
    },
    {
      "id": 7,
      "title": "Task Latency by Status",
      "type": "timeseries",
      "gridPos": { "x": 12, "y": 12, "w": 12, "h": 8 },
      "datasource": { "type": "prometheus", "uid": "prometheus" },
      "targets": [
        {
          "expr": "hi_jetstream_task_latency_seconds",
          "legendFormat": "{{status}}",
          "refId": "A"
        }
      ],
      "fieldConfig": {
        "defaults": { "unit": "s" }
      }
    },
    {
      "id": 8,
      "title": "Consumer Last Sequence (Lag Proxy)",
      "type": "timeseries",
      "gridPos": { "x": 0, "y": 20, "w": 24, "h": 6 },
      "datasource": { "type": "prometheus", "uid": "prometheus" },
      "targets": [
        {
          "expr": "hi_jetstream_consumer_last_seq",
          "legendFormat": "{{stream}}",
          "refId": "A"
        }
      ],
      "fieldConfig": {
        "defaults": { "unit": "short" }
      }
    }
  ]
}
